LICENSE
README.rst
setup.py
nfc_http_requester/__init__.py
nfc_http_requester/nfc_http_requester.py
nfc_http_requester.egg-info/PKG-INFO
nfc_http_requester.egg-info/SOURCES.txt
nfc_http_requester.egg-info/dependency_links.txt
nfc_http_requester.egg-info/entry_points.txt
nfc_http_requester.egg-info/requires.txt
nfc_http_requester.egg-info/top_level.txt